pygments_vsc_style/__init__.py
pygments_vsc_style/vsc.py
pygments_vsc_style-0.0.3.dist-info/LICENSE
pygments_vsc_style-0.0.3.dist-info/METADATA
pygments_vsc_style-0.0.3.dist-info/WHEEL
pygments_vsc_style-0.0.3.dist-info/entry_points.txt
pygments_vsc_style-0.0.3.dist-info/top_level.txt
pygments_vsc_style-0.0.3.dist-info/RECORD
