Metadata-Version: 2.1
Name: pygments-vsc-style
Version: 0.0.3
Summary: A pygments style inspired by vsc.
Home-page: https://github.com/Cryptex-github/pygments-vsc-style
Author: Cryptex
License: MIT
Project-URL: Issue tracker, https://github.com/Cryptex-github/pygments-vsc-style/issues
Platform: UNKNOWN
Classifier: License :: OSI Approved :: MIT License
Classifier: Intended Audience :: Developers
Classifier: Natural Language :: English
Classifier: Operating System :: OS Independent
Classifier: Programming Language :: Python :: 3.8
Classifier: Programming Language :: Python :: 3.9
Classifier: Topic :: Software Development :: Libraries
Classifier: Topic :: Software Development :: Libraries :: Python Modules
Classifier: Topic :: Utilities
Requires-Python: >=3.8.0
License-File: LICENSE
Requires-Dist: pygments (>=2.9.0)
